{"type":"FeatureCollection", "features": [
{"type":"Feature","geometry":{"type":"Point","coordinates":[334668.01910000015,368947.71189999953]},"properties":{"NODE_ID":"3690223701","NODE_TYPE":"101","NODE_NAME":"칠곡JC","TURN_P":"0","UPDATEDATE":"20230519","REMARK":"","HIST_TYPE":"","HISTREMARK":""}},
{"type":"Feature","geometry":{"type":"Point","coordinates":[386387.09810000006,310761.21880000085]},"properties":{"NODE_ID":"3880146200","NODE_TYPE":"106","NODE_NAME":"양산IC","TURN_P":"1","UPDATEDATE":"20230519","REMARK":"","HIST_TYPE":"","HISTREMARK":""}},
{"type":"Feature","geometry":{"type":"Point","coordinates":[207298.58150000032,535389.4119000006]},"properties":{"NODE_ID":"2040142800","NODE_TYPE":"106","NODE_NAME":"금토JC","TURN_P":"1","UPDATEDATE":"20230519","REMARK":"","HIST_TYPE":"","HISTREMARK":""}},
{"type":"Feature","geometry":{"type":"Point","coordinates":[392491.01020000037,330316.7240999993]},"properties":{"NODE_ID":"1960008800","NODE_TYPE":"101","NODE_NAME":"서울산IC","TURN_P":"0","UPDATEDATE":"20230519","REMARK":"","HIST_TYPE":"","HISTREMARK":""}},
{"type":"Feature","geometry":{"type":"Point","coordinates":[392722.59360000025,330942.0939000007]},"properties":{"NODE_ID":"1960009700","NODE_TYPE":"106","NODE_NAME":"서울산IC","TURN_P":"0","UPDATEDATE":"20230519","REMARK":"","HIST_TYPE":"","HISTREMARK":""}},
{"type":"Feature","geometry":{"type":"Point","coordinates":[281432.77109999955,403048.5069999993]},"properties":{"NODE_ID":"2770105200","NODE_TYPE":"106","NODE_NAME":"황간IC","TURN_P":"0","UPDATEDATE":"20230519","REMARK":"","HIST_TYPE":"","HISTREMARK":""}},
{"type":"Feature","geometry":{"type":"Point","coordinates":[202352.85149999987,542447.9796999991]},"properties":{"NODE_ID":"1210000900","NODE_TYPE":"106","NODE_NAME":"서초IC","TURN_P":"0","UPDATEDATE":"20230519","REMARK":"","HIST_TYPE":"","HISTREMARK":""}},
{"type":"Feature","geometry":{"type":"Point","coordinates":[202373.53949999996,542674.8999000005]},"properties":{"NODE_ID":"1210022400","NODE_TYPE":"106","NODE_NAME":"서초IC","TURN_P":"0","UPDATEDATE":"20230519","REMARK":"","HIST_TYPE":"","HISTREMARK":""}},
{"type":"Feature","geometry":{"type":"Point","coordinates":[349528.7050000001,369471.47589999996]},"properties":{"NODE_ID":"1510018300","NODE_TYPE":"106","NODE_NAME":"도동JC","TURN_P":"0","UPDATEDATE":"20230519","REMARK":"","HIST_TYPE":"","HISTREMARK":""}},
{"type":"Feature","geometry":{"type":"Point","coordinates":[342789.5717000002,369293.89130000025]},"properties":{"NODE_ID":"1540004400","NODE_TYPE":"106","NODE_NAME":"북대구IC","TURN_P":"0","UPDATEDATE":"20230519","REMARK":"","HIST_TYPE":"","HISTREMARK":""}},
{"type":"Feature","geometry":{"type":"Point","coordinates":[331055.4620000003,374101.73670000024]},"properties":{"NODE_ID":"3690016100","NODE_TYPE":"106","NODE_NAME":"칠곡물류IC","TURN_P":"1","UPDATEDATE":"20230519","REMARK":"","HIST_TYPE":"","HISTREMARK":""}},
{"type":"Feature","geometry":{"type":"Point","coordinates":[207722.24120000005,512923.70900000073]},"properties":{"NODE_ID":"2330518301","NODE_TYPE":"106","NODE_NAME":"기흥동탄IC","TURN_P":"0","UPDATEDATE":"20230519","REMARK":"","HIST_TYPE":"","HISTREMARK":""}},
{"type":"Feature","geometry":{"type":"Point","coordinates":[389713.8805999998,323349.0395999998]},"properties":{"NODE_ID":"3880014300","NODE_TYPE":"106","NODE_NAME":"통도사IC","TURN_P":"1","UPDATEDATE":"20230519","REMARK":"","HIST_TYPE":"","HISTREMARK":""}},
{"type":"Feature","geometry":{"type":"Point","coordinates":[386518.6436999999,311293.70529999956]},"properties":{"NODE_ID":"3880146300","NODE_TYPE":"106","NODE_NAME":"양산IC","TURN_P":"1","UPDATEDATE":"20230519","REMARK":"","HIST_TYPE":"","HISTREMARK":""}},
{"type":"Feature","geometry":{"type":"Point","coordinates":[353315.9215000002,366971.02779999934]},"properties":{"NODE_ID":"1510213901","NODE_TYPE":"101","NODE_NAME":"동대구JC","TURN_P":"0","UPDATEDATE":"20230519","REMARK":"","HIST_TYPE":"","HISTREMARK":""}},
{"type":"Feature","geometry":{"type":"Point","coordinates":[243946.75310000032,416599.26960000023]},"properties":{"NODE_ID":"1830073300","NODE_TYPE":"106","NODE_NAME":"비룡IC","TURN_P":"0","UPDATEDATE":"20230519","REMARK":"","HIST_TYPE":"","HISTREMARK":""}},
{"type":"Feature","geometry":{"type":"Point","coordinates":[237625.99409999978,427349.67090000026]},"properties":{"NODE_ID":"1870075300","NODE_TYPE":"106","NODE_NAME":"신탄진IC","TURN_P":"1","UPDATEDATE":"20230519","REMARK":"","HIST_TYPE":"","HISTREMARK":""}},
{"type":"Feature","geometry":{"type":"Point","coordinates":[392463.40249999985,330644.1623999998]},"properties":{"NODE_ID":"1960009000","NODE_TYPE":"106","NODE_NAME":"서울산IC","TURN_P":"1","UPDATEDATE":"20230519","REMARK":"","HIST_TYPE":"","HISTREMARK":""}},
{"type":"Feature","geometry":{"type":"Point","coordinates":[208988.1838999996,532856.0801999997]},"properties":{"NODE_ID":"2060099600","NODE_TYPE":"106","NODE_NAME":"판교IC","TURN_P":"0","UPDATEDATE":"20230519","REMARK":"","HIST_TYPE":"","HISTREMARK":""}},
{"type":"Feature","geometry":{"type":"Point","coordinates":[250192.49849999975,413128.0764000006]},"properties":{"NODE_ID":"2760149100","NODE_TYPE":"106","NODE_NAME":"옥천IC","TURN_P":"0","UPDATEDATE":"20230519","REMARK":"","HIST_TYPE":"","HISTREMARK":""}},
{"type":"Feature","geometry":{"type":"Point","coordinates":[202305.56960000005,542611.5837999992]},"properties":{"NODE_ID":"1210021900","NODE_TYPE":"106","NODE_NAME":"서초IC","TURN_P":"0","UPDATEDATE":"20230519","REMARK":"","HIST_TYPE":"","HISTREMARK":""}},
{"type":"Feature","geometry":{"type":"Point","coordinates":[201556.66500000004,546938.7216999996]},"properties":{"NODE_ID":"1210050100","NODE_TYPE":"106","NODE_NAME":"한남IC","TURN_P":"0","UPDATEDATE":"20230519","REMARK":"","HIST_TYPE":"","HISTREMARK":""}},
{"type":"Feature","geometry":{"type":"Point","coordinates":[322692.7488000002,391122.45490000024]},"properties":{"NODE_ID":"3550057500","NODE_TYPE":"106","NODE_NAME":"구미IC","TURN_P":"1","UPDATEDATE":"20230519","REMARK":"","HIST_TYPE":"","HISTREMARK":""}},
{"type":"Feature","geometry":{"type":"Point","coordinates":[391041.39609999955,300994.2575000003]},"properties":{"NODE_ID":"1400060200","NODE_TYPE":"106","NODE_NAME":"노포IC","TURN_P":"1","UPDATEDATE":"20230519","REMARK":"","HIST_TYPE":"","HISTREMARK":""}},
{"type":"Feature","geometry":{"type":"Point","coordinates":[338325.5312000001,367288.0406999998]},"properties":{"NODE_ID":"1540001100","NODE_TYPE":"106","NODE_NAME":"금호JC","TURN_P":"0","UPDATEDATE":"20230519","REMARK":"","HIST_TYPE":"","HISTREMARK":""}},
{"type":"Feature","geometry":{"type":"Point","coordinates":[349501.8842000002,369820.9006999992]},"properties":{"NODE_ID":"1510018700","NODE_TYPE":"106","NODE_NAME":"도동JC","TURN_P":"1","UPDATEDATE":"20230519","REMARK":"","HIST_TYPE":"","HISTREMARK":""}},
{"type":"Feature","geometry":{"type":"Point","coordinates":[207762.37689999957,512936.5508999992]},"properties":{"NODE_ID":"2330518501","NODE_TYPE":"106","NODE_NAME":"기흥동탄IC","TURN_P":"0","UPDATEDATE":"20230519","REMARK":"","HIST_TYPE":"","HISTREMARK":""}},
{"type":"Feature","geometry":{"type":"Point","coordinates":[298502.1294999998,393449.6122999992]},"properties":{"NODE_ID":"3530110600","NODE_TYPE":"106","NODE_NAME":"김천IC","TURN_P":"0","UPDATEDATE":"20230519","REMARK":"","HIST_TYPE":"","HISTREMARK":""}},
{"type":"Feature","geometry":{"type":"Point","coordinates":[207938.45440000016,533865.1372999996]},"properties":{"NODE_ID":"2040000100","NODE_TYPE":"106","NODE_NAME":"판교JC","TURN_P":"1","UPDATEDATE":"20230519","REMARK":"","HIST_TYPE":"","HISTREMARK":""}},
{"type":"Feature","geometry":{"type":"Point","coordinates":[233120.75210000016,451454.5123999994]},"properties":{"NODE_ID":"2710229400","NODE_TYPE":"106","NODE_NAME":"옥산하이패스IC","TURN_P":"0","UPDATEDATE":"20230519","REMARK":"","HIST_TYPE":"","HISTREMARK":""}},
{"type":"Feature","geometry":{"type":"Point","coordinates":[237972.91550000012,443946.8677999992]},"properties":{"NODE_ID":"2830014700","NODE_TYPE":"106","NODE_NAME":"남이JC","TURN_P":"1","UPDATEDATE":"20230519","REMARK":"","HIST_TYPE":"","HISTREMARK":""}},
{"type":"Feature","geometry":{"type":"Point","coordinates":[239084.87899999972,440686.5711000003]},"properties":{"NODE_ID":"2830021600","NODE_TYPE":"106","NODE_NAME":"청주JC","TURN_P":"0","UPDATEDATE":"20230519","REMARK":"","HIST_TYPE":"","HISTREMARK":""}},
{"type":"Feature","geometry":{"type":"Point","coordinates":[207642.29609999992,513144.1875]},"properties":{"NODE_ID":"2330518601","NODE_TYPE":"106","NODE_NAME":"기흥동탄IC","TURN_P":"0","UPDATEDATE":"20230519","REMARK":"","HIST_TYPE":"","HISTREMARK":""}},
{"type":"Feature","geometry":{"type":"Point","coordinates":[203474.23379999958,540415.5951000005]},"properties":{"NODE_ID":"1210012500","NODE_TYPE":"101","NODE_NAME":"양재IC","TURN_P":"0","UPDATEDATE":"20230519","REMARK":"","HIST_TYPE":"","HISTREMARK":""}},
{"type":"Feature","geometry":{"type":"Point","coordinates":[376406.8744000001,371206.6457000002]},"properties":{"NODE_ID":"3570001500","NODE_TYPE":"106","NODE_NAME":"영천IC","TURN_P":"0","UPDATEDATE":"20230519","REMARK":"","HIST_TYPE":"","HISTREMARK":""}},
{"type":"Feature","geometry":{"type":"Point","coordinates":[215384.41480000038,470295.9132000003]},"properties":{"NODE_ID":"3010092700","NODE_TYPE":"106","NODE_NAME":"천안IC","TURN_P":"0","UPDATEDATE":"20230519","REMARK":"","HIST_TYPE":"","HISTREMARK":""}},
{"type":"Feature","geometry":{"type":"Point","coordinates":[337649.79449999984,367703.6972000003]},"properties":{"NODE_ID":"1540001800","NODE_TYPE":"106","NODE_NAME":"금호JC","TURN_P":"0","UPDATEDATE":"20230519","REMARK":"","HIST_TYPE":"","HISTREMARK":""}},
{"type":"Feature","geometry":{"type":"Point","coordinates":[353420.8289999999,366383.9770999998]},"properties":{"NODE_ID":"1510003100","NODE_TYPE":"101","NODE_NAME":"동대구JC","TURN_P":"0","UPDATEDATE":"20230519","REMARK":"","HIST_TYPE":"","HISTREMARK":""}},
{"type":"Feature","geometry":{"type":"Point","coordinates":[317425.4567999998,394589.2542000003]},"properties":{"NODE_ID":"3550272001","NODE_TYPE":"106","NODE_NAME":"북구미하이패스IC","TURN_P":"0","UPDATEDATE":"20230519","REMARK":"","HIST_TYPE":"","HISTREMARK":""}},
{"type":"Feature","geometry":{"type":"Point","coordinates":[334542.48309999984,368648.40860000066]},"properties":{"NODE_ID":"3690223001","NODE_TYPE":"101","NODE_NAME":"칠곡JC","TURN_P":"0","UPDATEDATE":"20230519","REMARK":"","HIST_TYPE":"","HISTREMARK":""}},
{"type":"Feature","geometry":{"type":"Point","coordinates":[208040.8228000002,508783.5332999993]},"properties":{"NODE_ID":"2330120100","NODE_TYPE":"106","NODE_NAME":"동탄JC","TURN_P":"0","UPDATEDATE":"20230519","REMARK":"","HIST_TYPE":"","HISTREMARK":""}},
{"type":"Feature","geometry":{"type":"Point","coordinates":[237621.7745000003,426683.8490999993]},"properties":{"NODE_ID":"1870075200","NODE_TYPE":"106","NODE_NAME":"신탄진IC","TURN_P":"1","UPDATEDATE":"20230519","REMARK":"","HIST_TYPE":"","HISTREMARK":""}},
{"type":"Feature","geometry":{"type":"Point","coordinates":[209163.43719999958,518767.35419999994]},"properties":{"NODE_ID":"2440326800","NODE_TYPE":"106","NODE_NAME":"수원신갈IC","TURN_P":"0","UPDATEDATE":"20230519","REMARK":"","HIST_TYPE":"","HISTREMARK":""}},
{"type":"Feature","geometry":{"type":"Point","coordinates":[202228.7605999997,542873.4255999997]},"properties":{"NODE_ID":"1210025600","NODE_TYPE":"106","NODE_NAME":"서초IC","TURN_P":"0","UPDATEDATE":"20230519","REMARK":"","HIST_TYPE":"","HISTREMARK":""}},
{"type":"Feature","geometry":{"type":"Point","coordinates":[219518.69969999976,462228.6624999996]},"properties":{"NODE_ID":"3010104000","NODE_TYPE":"106","NODE_NAME":"목천IC","TURN_P":"1","UPDATEDATE":"20230519","REMARK":"","HIST_TYPE":"","HISTREMARK":""}},
{"type":"Feature","geometry":{"type":"Point","coordinates":[329007.66089999955,376723.5449999999]},"properties":{"NODE_ID":"3690068800","NODE_TYPE":"106","NODE_NAME":"왜관IC","TURN_P":"1","UPDATEDATE":"20230519","REMARK":"","HIST_TYPE":"","HISTREMARK":""}},
{"type":"Feature","geometry":{"type":"Point","coordinates":[329432.85080000013,376246.0111999996]},"properties":{"NODE_ID":"3690069600","NODE_TYPE":"106","NODE_NAME":"왜관IC","TURN_P":"1","UPDATEDATE":"20230519","REMARK":"","HIST_TYPE":"","HISTREMARK":""}},
{"type":"Feature","geometry":{"type":"Point","coordinates":[353264.33380000014,366493.7475000005]},"properties":{"NODE_ID":"1510212701","NODE_TYPE":"101","NODE_NAME":"동대구JC","TURN_P":"0","UPDATEDATE":"20230519","REMARK":"","HIST_TYPE":"","HISTREMARK":""}},
{"type":"Feature","geometry":{"type":"Point","coordinates":[398208.9375,347975.4382000007]},"properties":{"NODE_ID":"1960317400","NODE_TYPE":"106","NODE_NAME":"활천IC","TURN_P":"0","UPDATEDATE":"20230519","REMARK":"","HIST_TYPE":"","HISTREMARK":""}},
{"type":"Feature","geometry":{"type":"Point","coordinates":[237593.54569999967,445218.12900000066]},"properties":{"NODE_ID":"2710000200","NODE_TYPE":"106","NODE_NAME":"남이JC","TURN_P":"0","UPDATEDATE":"20230519","REMARK":"","HIST_TYPE":"","HISTREMARK":""}},
{"type":"Feature","geometry":{"type":"Point","coordinates":[215850.3331000004,464058.1831]},"properties":{"NODE_ID":"3010095600","NODE_TYPE":"101","NODE_NAME":"천안JC","TURN_P":"0","UPDATEDATE":"20230519","REMARK":"","HIST_TYPE":"","HISTREMARK":""}},
{"type":"Feature","geometry":{"type":"Point","coordinates":[314512.8660000004,396162.13269999996]},"properties":{"NODE_ID":"3530017000","NODE_TYPE":"106","NODE_NAME":"김천JC","TURN_P":"1","UPDATEDATE":"20230519","REMARK":"","HIST_TYPE":"","HISTREMARK":""}},
{"type":"Feature","geometry":{"type":"Point","coordinates":[203782.8267000001,540135.8361000009]},"properties":{"NODE_ID":"1210011400","NODE_TYPE":"106","NODE_NAME":"양재IC","TURN_P":"0","UPDATEDATE":"20230519","REMARK":"","HIST_TYPE":"","HISTREMARK":""}},
{"type":"Feature","geometry":{"type":"Point","coordinates":[202228.3071999997,542661.8923000004]},"properties":{"NODE_ID":"1210022500","NODE_TYPE":"106","NODE_NAME":"서초IC","TURN_P":"0","UPDATEDATE":"20230519","REMARK":"","HIST_TYPE":"","HISTREMARK":""}},
{"type":"Feature","geometry":{"type":"Point","coordinates":[204262.90579999983,539485.8720999993]},"properties":{"NODE_ID":"1210074700","NODE_TYPE":"106","NODE_NAME":"신양재IC","TURN_P":"1","UPDATEDATE":"20230519","REMARK":"","HIST_TYPE":"","HISTREMARK":""}},
{"type":"Feature","geometry":{"type":"Point","coordinates":[352800.24480000045,366509.3826000001]},"properties":{"NODE_ID":"1510212101","NODE_TYPE":"101","NODE_NAME":"동대구JC","TURN_P":"0","UPDATEDATE":"20230519","REMARK":"","HIST_TYPE":"","HISTREMARK":""}},
{"type":"Feature","geometry":{"type":"Point","coordinates":[334824.50019999966,368332.68180000037]},"properties":{"NODE_ID":"3690222901","NODE_TYPE":"101","NODE_NAME":"칠곡JC","TURN_P":"0","UPDATEDATE":"20230519","REMARK":"","HIST_TYPE":"","HISTREMARK":""}},
{"type":"Feature","geometry":{"type":"Point","coordinates":[208537.37660000008,508786.27419999987]},"properties":{"NODE_ID":"2330526601","NODE_TYPE":"106","NODE_NAME":"동탄JC","TURN_P":"0","UPDATEDATE":"20230519","REMARK":"","HIST_TYPE":"","HISTREMARK":""}},
{"type":"Feature","geometry":{"type":"Point","coordinates":[250914.2028000001,412565.4704]},"properties":{"NODE_ID":"2760149400","NODE_TYPE":"106","NODE_NAME":"옥천IC","TURN_P":"1","UPDATEDATE":"20230519","REMARK":"","HIST_TYPE":"","HISTREMARK":""}},
{"type":"Feature","geometry":{"type":"Point","coordinates":[298023.1127000004,393484.82359999977]},"properties":{"NODE_ID":"3530014400","NODE_TYPE":"106","NODE_NAME":"김천IC","TURN_P":"0","UPDATEDATE":"20230519","REMARK":"","HIST_TYPE":"","HISTREMARK":""}},
{"type":"Feature","geometry":{"type":"Point","coordinates":[313341.3788999999,396686.9503000006]},"properties":{"NODE_ID":"3530017600","NODE_TYPE":"106","NODE_NAME":"김천JC","TURN_P":"1","UPDATEDATE":"20230519","REMARK":"","HIST_TYPE":"","HISTREMARK":""}},
{"type":"Feature","geometry":{"type":"Point","coordinates":[350483.9210999999,370158.16860000044]},"properties":{"NODE_ID":"1510004700","NODE_TYPE":"106","NODE_NAME":"도동JC","TURN_P":"0","UPDATEDATE":"20230519","REMARK":"","HIST_TYPE":"","HISTREMARK":""}},
{"type":"Feature","geometry":{"type":"Point","coordinates":[337756.5076000001,366838.48069999926]},"properties":{"NODE_ID":"1540000100","NODE_TYPE":"106","NODE_NAME":"금호JC","TURN_P":"0","UPDATEDATE":"20230519","REMARK":"","HIST_TYPE":"","HISTREMARK":""}},
{"type":"Feature","geometry":{"type":"Point","coordinates":[216905.5438000001,463175.0212999992]},"properties":{"NODE_ID":"3010098700","NODE_TYPE":"101","NODE_NAME":"천안JC","TURN_P":"0","UPDATEDATE":"20230519","REMARK":"","HIST_TYPE":"","HISTREMARK":""}},
{"type":"Feature","geometry":{"type":"Point","coordinates":[219693.86990000028,462431.1754999999]},"properties":{"NODE_ID":"3010104700","NODE_TYPE":"106","NODE_NAME":"목천IC","TURN_P":"0","UPDATEDATE":"20230519","REMARK":"","HIST_TYPE":"","HISTREMARK":""}},
{"type":"Feature","geometry":{"type":"Point","coordinates":[353080.0366000002,366629.50569999963]},"properties":{"NODE_ID":"1510212601","NODE_TYPE":"101","NODE_NAME":"동대구JC","TURN_P":"0","UPDATEDATE":"20230519","REMARK":"","HIST_TYPE":"","HISTREMARK":""}},
{"type":"Feature","geometry":{"type":"Point","coordinates":[203591.58669999987,540493.7884999998]},"properties":{"NODE_ID":"1210013100","NODE_TYPE":"101","NODE_NAME":"양재IC","TURN_P":"0","UPDATEDATE":"20230519","REMARK":"","HIST_TYPE":"","HISTREMARK":""}},
{"type":"Feature","geometry":{"type":"Point","coordinates":[237794.02240000013,423622.15359999985]},"properties":{"NODE_ID":"1870001900","NODE_TYPE":"106","NODE_NAME":"회덕JC","TURN_P":"0","UPDATEDATE":"20230519","REMARK":"","HIST_TYPE":"","HISTREMARK":""}},
{"type":"Feature","geometry":{"type":"Point","coordinates":[240759.03369999956,418069.83669999987]},"properties":{"NODE_ID":"1870078600","NODE_TYPE":"106","NODE_NAME":"대전IC","TURN_P":"0","UPDATEDATE":"20230519","REMARK":"","HIST_TYPE":"","HISTREMARK":""}},
{"type":"Feature","geometry":{"type":"Point","coordinates":[203498.00870000012,540511.1368000004]},"properties":{"NODE_ID":"1210013400","NODE_TYPE":"106","NODE_NAME":"양재IC","TURN_P":"0","UPDATEDATE":"20230519","REMARK":"","HIST_TYPE":"","HISTREMARK":""}},
{"type":"Feature","geometry":{"type":"Point","coordinates":[201328.98039999977,545519.4935999997]},"properties":{"NODE_ID":"1210044700","NODE_TYPE":"106","NODE_NAME":"잠원IC","TURN_P":"0","UPDATEDATE":"20230519","REMARK":"","HIST_TYPE":"","HISTREMARK":""}},
{"type":"Feature","geometry":{"type":"Point","coordinates":[204101.5833999999,539764.0800999999]},"properties":{"NODE_ID":"1210074300","NODE_TYPE":"106","NODE_NAME":"양재IC","TURN_P":"0","UPDATEDATE":"20230519","REMARK":"","HIST_TYPE":"","HISTREMARK":""}},
{"type":"Feature","geometry":{"type":"Point","coordinates":[214883.48599999957,469777.4787000008]},"properties":{"NODE_ID":"3010090200","NODE_TYPE":"106","NODE_NAME":"천안IC","TURN_P":"0","UPDATEDATE":"20230519","REMARK":"","HIST_TYPE":"","HISTREMARK":""}},
{"type":"Feature","geometry":{"type":"Point","coordinates":[207763.68730000034,512905.4026999995]},"properties":{"NODE_ID":"2330496100","NODE_TYPE":"106","NODE_NAME":"기흥동탄IC","TURN_P":"0","UPDATEDATE":"20230519","REMARK":"","HIST_TYPE":"","HISTREMARK":""}},
{"type":"Feature","geometry":{"type":"Point","coordinates":[317134.95529999956,394639.2541000005]},"properties":{"NODE_ID":"3550271801","NODE_TYPE":"106","NODE_NAME":"북구미하이패스IC","TURN_P":"0","UPDATEDATE":"20230519","REMARK":"","HIST_TYPE":"","HISTREMARK":""}},
{"type":"Feature","geometry":{"type":"Point","coordinates":[202379.8417999996,542412.2169000003]},"properties":{"NODE_ID":"1210020300","NODE_TYPE":"106","NODE_NAME":"서초IC","TURN_P":"0","UPDATEDATE":"20230519","REMARK":"","HIST_TYPE":"","HISTREMARK":""}},
{"type":"Feature","geometry":{"type":"Point","coordinates":[388597.15110000037,362411.1908]},"properties":{"NODE_ID":"3520017900","NODE_TYPE":"106","NODE_NAME":"건천IC","TURN_P":"1","UPDATEDATE":"20230519","REMARK":"","HIST_TYPE":"","HISTREMARK":""}},
{"type":"Feature","geometry":{"type":"Point","coordinates":[305618.2868999997,393507.4648000002]},"properties":{"NODE_ID":"3530023400","NODE_TYPE":"106","NODE_NAME":"동김천IC","TURN_P":"0","UPDATEDATE":"20230519","REMARK":"","HIST_TYPE":"","HISTREMARK":""}},
{"type":"Feature","geometry":{"type":"Point","coordinates":[305788.08270000014,393994.4648000002]},"properties":{"NODE_ID":"3530023600","NODE_TYPE":"106","NODE_NAME":"동김천IC","TURN_P":"1","UPDATEDATE":"20230519","REMARK":"","HIST_TYPE":"","HISTREMARK":""}},
{"type":"Feature","geometry":{"type":"Point","coordinates":[203338.49959999975,540276.1141999997]},"properties":{"NODE_ID":"1210000500","NODE_TYPE":"106","NODE_NAME":"양재IC","TURN_P":"0","UPDATEDATE":"20230519","REMARK":"","HIST_TYPE":"","HISTREMARK":""}},
{"type":"Feature","geometry":{"type":"Point","coordinates":[203716.3015999999,540197.0029000007]},"properties":{"NODE_ID":"1210011300","NODE_TYPE":"106","NODE_NAME":"양재IC","TURN_P":"0","UPDATEDATE":"20230519","REMARK":"","HIST_TYPE":"","HISTREMARK":""}},
{"type":"Feature","geometry":{"type":"Point","coordinates":[203486.7944,540499.4420999996]},"properties":{"NODE_ID":"1210013300","NODE_TYPE":"106","NODE_NAME":"양재IC","TURN_P":"0","UPDATEDATE":"20230519","REMARK":"","HIST_TYPE":"","HISTREMARK":""}},
{"type":"Feature","geometry":{"type":"Point","coordinates":[202108.37060000002,542628.9047999997]},"properties":{"NODE_ID":"1210021700","NODE_TYPE":"106","NODE_NAME":"서초IC","TURN_P":"0","UPDATEDATE":"20230519","REMARK":"","HIST_TYPE":"","HISTREMARK":""}},
{"type":"Feature","geometry":{"type":"Point","coordinates":[201533.82629999984,544858.8976000007]},"properties":{"NODE_ID":"1210038200","NODE_TYPE":"106","NODE_NAME":"반포IC","TURN_P":"0","UPDATEDATE":"20230519","REMARK":"","HIST_TYPE":"","HISTREMARK":""}},
{"type":"Feature","geometry":{"type":"Point","coordinates":[201351.5362999998,545804.2002000008]},"properties":{"NODE_ID":"1210046100","NODE_TYPE":"106","NODE_NAME":"잠원IC","TURN_P":"0","UPDATEDATE":"20230519","REMARK":"","HIST_TYPE":"","HISTREMARK":""}},
{"type":"Feature","geometry":{"type":"Point","coordinates":[208399.33029999956,513043.62560000084]},"properties":{"NODE_ID":"2330160000","NODE_TYPE":"106","NODE_NAME":"기흥동탄IC","TURN_P":"0","UPDATEDATE":"20230519","REMARK":"","HIST_TYPE":"","HISTREMARK":""}},
{"type":"Feature","geometry":{"type":"Point","coordinates":[381473.71449999977,371833.84080000035]},"properties":{"NODE_ID":"3570850900","NODE_TYPE":"106","NODE_NAME":"북안IC","TURN_P":"1","UPDATEDATE":"20230519","REMARK":"","HIST_TYPE":"","HISTREMARK":""}},
{"type":"Feature","geometry":{"type":"Point","coordinates":[216656.17980000004,477575.20299999975]},"properties":{"NODE_ID":"3020168500","NODE_TYPE":"106","NODE_NAME":"북천안IC","TURN_P":"0","UPDATEDATE":"20230519","REMARK":"","HIST_TYPE":"","HISTREMARK":""}},
{"type":"Feature","geometry":{"type":"Point","coordinates":[209108.91889999993,518418.2497000005]},"properties":{"NODE_ID":"2440040500","NODE_TYPE":"106","NODE_NAME":"수원신갈IC","TURN_P":"0","UPDATEDATE":"20230519","REMARK":"","HIST_TYPE":"","HISTREMARK":""}},
{"type":"Feature","geometry":{"type":"Point","coordinates":[316810.3844999997,394881.4907000009]},"properties":{"NODE_ID":"3550271601","NODE_TYPE":"106","NODE_NAME":"북구미하이패스IC","TURN_P":"0","UPDATEDATE":"20230519","REMARK":"","HIST_TYPE":"","HISTREMARK":""}},
{"type":"Feature","geometry":{"type":"Point","coordinates":[237521.13520000037,422700.42610000074]},"properties":{"NODE_ID":"1870001500","NODE_TYPE":"106","NODE_NAME":"회덕JC","TURN_P":"0","UPDATEDATE":"20230519","REMARK":"","HIST_TYPE":"","HISTREMARK":""}},
{"type":"Feature","geometry":{"type":"Point","coordinates":[208684.76180000044,534176.8230000008]},"properties":{"NODE_ID":"2040000200","NODE_TYPE":"106","NODE_NAME":"판교JC","TURN_P":"1","UPDATEDATE":"20230519","REMARK":"","HIST_TYPE":"","HISTREMARK":""}},
{"type":"Feature","geometry":{"type":"Point","coordinates":[238352.70779999997,437339.89499999955]},"properties":{"NODE_ID":"2830017500","NODE_TYPE":"106","NODE_NAME":"남청주IC","TURN_P":"0","UPDATEDATE":"20230519","REMARK":"","HIST_TYPE":"","HISTREMARK":""}},
{"type":"Feature","geometry":{"type":"Point","coordinates":[397650.85089999996,358643.8169999998]},"properties":{"NODE_ID":"3520012300","NODE_TYPE":"106","NODE_NAME":"경주IC","TURN_P":"1","UPDATEDATE":"20230519","REMARK":"","HIST_TYPE":"","HISTREMARK":""}},
{"type":"Feature","geometry":{"type":"Point","coordinates":[388297.67760000005,362647.0713999998]},"properties":{"NODE_ID":"3520019100","NODE_TYPE":"106","NODE_NAME":"건천IC","TURN_P":"1","UPDATEDATE":"20230519","REMARK":"","HIST_TYPE":"","HISTREMARK":""}},
{"type":"Feature","geometry":{"type":"Point","coordinates":[375632.1974999998,371151.0979999993]},"properties":{"NODE_ID":"3570001400","NODE_TYPE":"106","NODE_NAME":"영천IC","TURN_P":"0","UPDATEDATE":"20230519","REMARK":"","HIST_TYPE":"","HISTREMARK":""}},
{"type":"Feature","geometry":{"type":"Point","coordinates":[390803.53890000004,301244.6819000002]},"properties":{"NODE_ID":"1400060000","NODE_TYPE":"106","NODE_NAME":"노포IC","TURN_P":"1","UPDATEDATE":"20230519","REMARK":"","HIST_TYPE":"","HISTREMARK":""}},
{"type":"Feature","geometry":{"type":"Point","coordinates":[391176.52689999994,301336.6214000005]},"properties":{"NODE_ID":"1400060500","NODE_TYPE":"106","NODE_NAME":"노포IC","TURN_P":"0","UPDATEDATE":"20230519","REMARK":"","HIST_TYPE":"","HISTREMARK":""}},
{"type":"Feature","geometry":{"type":"Point","coordinates":[216860.64169999957,477408.1662000008]},"properties":{"NODE_ID":"3020169300","NODE_TYPE":"106","NODE_NAME":"북천안IC","TURN_P":"1","UPDATEDATE":"20230519","REMARK":"","HIST_TYPE":"","HISTREMARK":""}},
{"type":"Feature","geometry":{"type":"Point","coordinates":[342903.30429999996,369162.9782999996]},"properties":{"NODE_ID":"1540004300","NODE_TYPE":"106","NODE_NAME":"북대구IC","TURN_P":"0","UPDATEDATE":"20230519","REMARK":"","HIST_TYPE":"","HISTREMARK":""}},
{"type":"Feature","geometry":{"type":"Point","coordinates":[328988.1814000001,376438.9605999999]},"properties":{"NODE_ID":"3690138300","NODE_TYPE":"106","NODE_NAME":"왜관IC","TURN_P":"1","UPDATEDATE":"20230519","REMARK":"","HIST_TYPE":"","HISTREMARK":""}},
{"type":"Feature","geometry":{"type":"Point","coordinates":[334371.0700000003,369443.95900000073]},"properties":{"NODE_ID":"3690224101","NODE_TYPE":"101","NODE_NAME":"칠곡JC","TURN_P":"0","UPDATEDATE":"20230519","REMARK":"","HIST_TYPE":"","HISTREMARK":""}},
{"type":"Feature","geometry":{"type":"Point","coordinates":[208978.24349999987,532678.2762000002]},"properties":{"NODE_ID":"2060004100","NODE_TYPE":"106","NODE_NAME":"판교IC","TURN_P":"1","UPDATEDATE":"20230519","REMARK":"","HIST_TYPE":"","HISTREMARK":""}},
{"type":"Feature","geometry":{"type":"Point","coordinates":[203341.08160000015,540691.8955000006]},"properties":{"NODE_ID":"1210000800","NODE_TYPE":"106","NODE_NAME":"양재IC","TURN_P":"0","UPDATEDATE":"20230519","REMARK":"","HIST_TYPE":"","HISTREMARK":""}},
{"type":"Feature","geometry":{"type":"Point","coordinates":[201704.39250000007,544618.8373000007]},"properties":{"NODE_ID":"1210036600","NODE_TYPE":"106","NODE_NAME":"반포IC","TURN_P":"0","UPDATEDATE":"20230519","REMARK":"","HIST_TYPE":"","HISTREMARK":""}},
{"type":"Feature","geometry":{"type":"Point","coordinates":[390538.7690000003,301324.84750000015]},"properties":{"NODE_ID":"1400059900","NODE_TYPE":"106","NODE_NAME":"노포JC","TURN_P":"0","UPDATEDATE":"20230519","REMARK":"","HIST_TYPE":"","HISTREMARK":""}},
{"type":"Feature","geometry":{"type":"Point","coordinates":[331197.1498999996,374552.9302999992]},"properties":{"NODE_ID":"3690016200","NODE_TYPE":"106","NODE_NAME":"칠곡물류IC","TURN_P":"1","UPDATEDATE":"20230519","REMARK":"","HIST_TYPE":"","HISTREMARK":""}},
{"type":"Feature","geometry":{"type":"Point","coordinates":[209207.30260000005,518520.7977000009]},"properties":{"NODE_ID":"2440042500","NODE_TYPE":"106","NODE_NAME":"수원신갈IC","TURN_P":"0","UPDATEDATE":"20230519","REMARK":"","HIST_TYPE":"","HISTREMARK":""}},
{"type":"Feature","geometry":{"type":"Point","coordinates":[385486.3905999996,306644.9291999992]},"properties":{"NODE_ID":"3880005400","NODE_TYPE":"106","NODE_NAME":"양산JC","TURN_P":"0","UPDATEDATE":"20230519","REMARK":"","HIST_TYPE":"","HISTREMARK":""}},
{"type":"Feature","geometry":{"type":"Point","coordinates":[208437.16440000013,508467.9024]},"properties":{"NODE_ID":"2330526201","NODE_TYPE":"106","NODE_NAME":"동탄JC","TURN_P":"0","UPDATEDATE":"20230519","REMARK":"","HIST_TYPE":"","HISTREMARK":""}},
{"type":"Feature","geometry":{"type":"Point","coordinates":[213503.6858000001,488497.83440000005]},"properties":{"NODE_ID":"2310003000","NODE_TYPE":"106","NODE_NAME":"안성IC","TURN_P":"1","UPDATEDATE":"20230519","REMARK":"","HIST_TYPE":"","HISTREMARK":""}},
{"type":"Feature","geometry":{"type":"Point","coordinates":[237773.44539999962,426885.5186999999]},"properties":{"NODE_ID":"1870002700","NODE_TYPE":"106","NODE_NAME":"신탄진IC","TURN_P":"1","UPDATEDATE":"20230519","REMARK":"","HIST_TYPE":"","HISTREMARK":""}},
{"type":"Feature","geometry":{"type":"Point","coordinates":[208801.3501000004,533247.6715999991]},"properties":{"NODE_ID":"2060060200","NODE_TYPE":"101","NODE_NAME":"판교IC","TURN_P":"0","UPDATEDATE":"20230519","REMARK":"","HIST_TYPE":"","HISTREMARK":""}},
{"type":"Feature","geometry":{"type":"Point","coordinates":[238516.07710000034,437115.2301000003]},"properties":{"NODE_ID":"2830019300","NODE_TYPE":"106","NODE_NAME":"남청주IC","TURN_P":"1","UPDATEDATE":"20230519","REMARK":"","HIST_TYPE":"","HISTREMARK":""}},
{"type":"Feature","geometry":{"type":"Point","coordinates":[202286.14460000023,542735.2037000004]},"properties":{"NODE_ID":"1210022900","NODE_TYPE":"106","NODE_NAME":"서초IC","TURN_P":"0","UPDATEDATE":"20230519","REMARK":"","HIST_TYPE":"","HISTREMARK":""}},
{"type":"Feature","geometry":{"type":"Point","coordinates":[201446.14549999963,546395.9417000003]},"properties":{"NODE_ID":"1210048000","NODE_TYPE":"106","NODE_NAME":"한남IC","TURN_P":"0","UPDATEDATE":"20230519","REMARK":"","HIST_TYPE":"","HISTREMARK":""}},
{"type":"Feature","geometry":{"type":"Point","coordinates":[201455.1183000002,546460.7763]},"properties":{"NODE_ID":"1210048700","NODE_TYPE":"106","NODE_NAME":"한남IC","TURN_P":"0","UPDATEDATE":"20230519","REMARK":"","HIST_TYPE":"","HISTREMARK":""}},
{"type":"Feature","geometry":{"type":"Point","coordinates":[376042.2410000004,371576.86620000005]},"properties":{"NODE_ID":"3570001800","NODE_TYPE":"106","NODE_NAME":"영천IC","TURN_P":"1","UPDATEDATE":"20230519","REMARK":"","HIST_TYPE":"","HISTREMARK":""}},
{"type":"Feature","geometry":{"type":"Point","coordinates":[381130.96279999986,370710.0365999993]},"properties":{"NODE_ID":"3570850800","NODE_TYPE":"106","NODE_NAME":"영천JC","TURN_P":"1","UPDATEDATE":"20230519","REMARK":"","HIST_TYPE":"","HISTREMARK":""}},
{"type":"Feature","geometry":{"type":"Point","coordinates":[240392.2882000003,418322.5471999999]},"properties":{"NODE_ID":"1870000600","NODE_TYPE":"106","NODE_NAME":"대전IC","TURN_P":"1","UPDATEDATE":"20230519","REMARK":"","HIST_TYPE":"","HISTREMARK":""}},
{"type":"Feature","geometry":{"type":"Point","coordinates":[389813.21970000025,323134.0418999996]},"properties":{"NODE_ID":"3880013900","NODE_TYPE":"106","NODE_NAME":"통도사IC","TURN_P":"1","UPDATEDATE":"20230519","REMARK":"","HIST_TYPE":"","HISTREMARK":""}},
{"type":"Feature","geometry":{"type":"Point","coordinates":[390645.64910000004,296596.40949999914]},"properties":{"NODE_ID":"1400003000","NODE_TYPE":"101","NODE_NAME":"구서IC","TURN_P":"1","UPDATEDATE":"20230519","REMARK":"","HIST_TYPE":"","HISTREMARK":""}},
{"type":"Feature","geometry":{"type":"Point","coordinates":[334704.81520000007,368826.5225000009]},"properties":{"NODE_ID":"3690223601","NODE_TYPE":"101","NODE_NAME":"칠곡JC","TURN_P":"0","UPDATEDATE":"20230519","REMARK":"","HIST_TYPE":"","HISTREMARK":""}},
{"type":"Feature","geometry":{"type":"Point","coordinates":[334765.4255999997,368389.91029999964]},"properties":{"NODE_ID":"3690222801","NODE_TYPE":"101","NODE_NAME":"칠곡JC","TURN_P":"0","UPDATEDATE":"20230519","REMARK":"","HIST_TYPE":"","HISTREMARK":""}},
{"type":"Feature","geometry":{"type":"Point","coordinates":[390012.00459999964,324704.2655999996]},"properties":{"NODE_ID":"1960316800","NODE_TYPE":"106","NODE_NAME":"통도사IC","TURN_P":"1","UPDATEDATE":"20230519","REMARK":"","HIST_TYPE":"","HISTREMARK":""}},
{"type":"Feature","geometry":{"type":"Point","coordinates":[251200.49689999968,412678.2497000005]},"properties":{"NODE_ID":"2760149800","NODE_TYPE":"106","NODE_NAME":"옥천IC","TURN_P":"0","UPDATEDATE":"20230519","REMARK":"","HIST_TYPE":"","HISTREMARK":""}},
{"type":"Feature","geometry":{"type":"Point","coordinates":[202225.53120000008,542941.0304000005]},"properties":{"NODE_ID":"1210001200","NODE_TYPE":"106","NODE_NAME":"서초IC","TURN_P":"0","UPDATEDATE":"20230519","REMARK":"","HIST_TYPE":"","HISTREMARK":""}},
{"type":"Feature","geometry":{"type":"Point","coordinates":[202272.1188000003,542726.1931999996]},"properties":{"NODE_ID":"1210022800","NODE_TYPE":"106","NODE_NAME":"서초IC","TURN_P":"0","UPDATEDATE":"20230519","REMARK":"","HIST_TYPE":"","HISTREMARK":""}},
{"type":"Feature","geometry":{"type":"Point","coordinates":[201538.1810999997,544870.0855999999]},"properties":{"NODE_ID":"1210038400","NODE_TYPE":"106","NODE_NAME":"반포IC","TURN_P":"0","UPDATEDATE":"20230519","REMARK":"","HIST_TYPE":"","HISTREMARK":""}},
{"type":"Feature","geometry":{"type":"Point","coordinates":[201618.11909999978,544887.4307000004]},"properties":{"NODE_ID":"1210038800","NODE_TYPE":"106","NODE_NAME":"반포IC","TURN_P":"0","UPDATEDATE":"20230519","REMARK":"","HIST_TYPE":"","HISTREMARK":""}},
{"type":"Feature","geometry":{"type":"Point","coordinates":[207951.44519999996,513723.3747000005]},"properties":{"NODE_ID":"2440031100","NODE_TYPE":"106","NODE_NAME":"기흥동탄IC","TURN_P":"1","UPDATEDATE":"20230519","REMARK":"","HIST_TYPE":"","HISTREMARK":""}},
{"type":"Feature","geometry":{"type":"Point","coordinates":[352537.65890000015,367035.2078000009]},"properties":{"NODE_ID":"1510212301","NODE_TYPE":"101","NODE_NAME":"동대구JC","TURN_P":"0","UPDATEDATE":"20230519","REMARK":"","HIST_TYPE":"","HISTREMARK":""}},
{"type":"Feature","geometry":{"type":"Point","coordinates":[334253.43489999976,368719.09259999916]},"properties":{"NODE_ID":"3690222601","NODE_TYPE":"101","NODE_NAME":"칠곡JC","TURN_P":"0","UPDATEDATE":"20230519","REMARK":"","HIST_TYPE":"","HISTREMARK":""}},
{"type":"Feature","geometry":{"type":"Point","coordinates":[335024.3761,368897.0705999993]},"properties":{"NODE_ID":"3690224301","NODE_TYPE":"101","NODE_NAME":"칠곡JC","TURN_P":"0","UPDATEDATE":"20230519","REMARK":"","HIST_TYPE":"","HISTREMARK":""}},
{"type":"Feature","geometry":{"type":"Point","coordinates":[207422.72140000015,534960.9675999992]},"properties":{"NODE_ID":"2040142900","NODE_TYPE":"106","NODE_NAME":"금토JC","TURN_P":"1","UPDATEDATE":"20230519","REMARK":"","HIST_TYPE":"","HISTREMARK":""}},
{"type":"Feature","geometry":{"type":"Point","coordinates":[243285.1825000001,416056.40809999965]},"properties":{"NODE_ID":"1830073100","NODE_TYPE":"106","NODE_NAME":"비룡JC","TURN_P":"0","UPDATEDATE":"20230519","REMARK":"","HIST_TYPE":"","HISTREMARK":""}},
{"type":"Feature","geometry":{"type":"Point","coordinates":[390221.89159999974,324784.22389999963]},"properties":{"NODE_ID":"1960317300","NODE_TYPE":"106","NODE_NAME":"통도사IC","TURN_P":"1","UPDATEDATE":"20230519","REMARK":"","HIST_TYPE":"","HISTREMARK":""}},
{"type":"Feature","geometry":{"type":"Point","coordinates":[388324.74909999967,362848.72330000065]},"properties":{"NODE_ID":"3520019600","NODE_TYPE":"106","NODE_NAME":"건천IC","TURN_P":"1","UPDATEDATE":"20230519","REMARK":"","HIST_TYPE":"","HISTREMARK":""}},
{"type":"Feature","geometry":{"type":"Point","coordinates":[201491.55530000012,546793.4923]},"properties":{"NODE_ID":"1210049100","NODE_TYPE":"106","NODE_NAME":"한남IC","TURN_P":"0","UPDATEDATE":"20230519","REMARK":"","HIST_TYPE":"","HISTREMARK":""}},
{"type":"Feature","geometry":{"type":"Point","coordinates":[391109.7829,297217.03229999915]},"properties":{"NODE_ID":"1400003500","NODE_TYPE":"106","NODE_NAME":"구서IC","TURN_P":"1","UPDATEDATE":"20230519","REMARK":"","HIST_TYPE":"","HISTREMARK":""}},
{"type":"Feature","geometry":{"type":"Point","coordinates":[214956.3861999996,469562.0688000005]},"properties":{"NODE_ID":"3010090300","NODE_TYPE":"106","NODE_NAME":"천안IC","TURN_P":"0","UPDATEDATE":"20230519","REMARK":"","HIST_TYPE":"","HISTREMARK":""}},
{"type":"Feature","geometry":{"type":"Point","coordinates":[350558.7726999996,369385.88460000046]},"properties":{"NODE_ID":"1510018100","NODE_TYPE":"106","NODE_NAME":"도동JC","TURN_P":"0","UPDATEDATE":"20230519","REMARK":"","HIST_TYPE":"","HISTREMARK":""}},
{"type":"Feature","geometry":{"type":"Point","coordinates":[331306.3021999998,373975.9120000005]},"properties":{"NODE_ID":"3690016000","NODE_TYPE":"106","NODE_NAME":"칠곡물류IC","TURN_P":"1","UPDATEDATE":"20230519","REMARK":"","HIST_TYPE":"","HISTREMARK":""}},
{"type":"Feature","geometry":{"type":"Point","coordinates":[207605.37260000035,513055.83249999955]},"properties":{"NODE_ID":"2330518401","NODE_TYPE":"101","NODE_NAME":"기흥동탄IC","TURN_P":"0","UPDATEDATE":"20230519","REMARK":"","HIST_TYPE":"","HISTREMARK":""}},
{"type":"Feature","geometry":{"type":"Point","coordinates":[334847.0747999996,368222.73819999956]},"properties":{"NODE_ID":"3690222701","NODE_TYPE":"101","NODE_NAME":"칠곡JC","TURN_P":"0","UPDATEDATE":"20230519","REMARK":"","HIST_TYPE":"","HISTREMARK":""}},
{"type":"Feature","geometry":{"type":"Point","coordinates":[393038.84729999956,331822.61620000005]},"properties":{"NODE_ID":"1960011800","NODE_TYPE":"106","NODE_NAME":"언양JC","TURN_P":"1","UPDATEDATE":"20230519","REMARK":"","HIST_TYPE":"","HISTREMARK":""}},
{"type":"Feature","geometry":{"type":"Point","coordinates":[393480.89279999956,331828.9140000008]},"properties":{"NODE_ID":"1960011900","NODE_TYPE":"106","NODE_NAME":"언양JC","TURN_P":"1","UPDATEDATE":"20230519","REMARK":"","HIST_TYPE":"","HISTREMARK":""}},
{"type":"Feature","geometry":{"type":"Point","coordinates":[275019.36120000016,408132.42640000023]},"properties":{"NODE_ID":"2770102800","NODE_TYPE":"106","NODE_NAME":"영동IC","TURN_P":"0","UPDATEDATE":"20230519","REMARK":"","HIST_TYPE":"","HISTREMARK":""}},
{"type":"Feature","geometry":{"type":"Point","coordinates":[234341.00409999955,447443.8992999997]},"properties":{"NODE_ID":"2710003400","NODE_TYPE":"106","NODE_NAME":"청주IC","TURN_P":"1","UPDATEDATE":"20230519","REMARK":"","HIST_TYPE":"","HISTREMARK":""}},
{"type":"Feature","geometry":{"type":"Point","coordinates":[238571.07710000034,437735.43879999965]},"properties":{"NODE_ID":"2830019900","NODE_TYPE":"106","NODE_NAME":"남청주IC","TURN_P":"1","UPDATEDATE":"20230519","REMARK":"","HIST_TYPE":"","HISTREMARK":""}},
{"type":"Feature","geometry":{"type":"Point","coordinates":[313894.48869999964,397079.15850000083]},"properties":{"NODE_ID":"3530017800","NODE_TYPE":"106","NODE_NAME":"김천JC","TURN_P":"0","UPDATEDATE":"20230519","REMARK":"","HIST_TYPE":"","HISTREMARK":""}},
{"type":"Feature","geometry":{"type":"Point","coordinates":[203353.19049999956,540702.4086000007]},"properties":{"NODE_ID":"1210013800","NODE_TYPE":"106","NODE_NAME":"양재IC","TURN_P":"0","UPDATEDATE":"20230519","REMARK":"","HIST_TYPE":"","HISTREMARK":""}},
{"type":"Feature","geometry":{"type":"Point","coordinates":[391835.0384999998,299231.32100000046]},"properties":{"NODE_ID":"1400004700","NODE_TYPE":"106","NODE_NAME":"영락IC","TURN_P":"1","UPDATEDATE":"20230519","REMARK":"","HIST_TYPE":"","HISTREMARK":""}},
{"type":"Feature","geometry":{"type":"Point","coordinates":[391404.8241999997,300617.1283]},"properties":{"NODE_ID":"1400060700","NODE_TYPE":"106","NODE_NAME":"노포JC","TURN_P":"1","UPDATEDATE":"20230519","REMARK":"","HIST_TYPE":"","HISTREMARK":""}},
{"type":"Feature","geometry":{"type":"Point","coordinates":[216854.62320000026,477939.9012000002]},"properties":{"NODE_ID":"3020169200","NODE_TYPE":"106","NODE_NAME":"북천안IC","TURN_P":"0","UPDATEDATE":"20230519","REMARK":"","HIST_TYPE":"","HISTREMARK":""}},
{"type":"Feature","geometry":{"type":"Point","coordinates":[349881.98560000025,369542.3047000002]},"properties":{"NODE_ID":"1510018400","NODE_TYPE":"106","NODE_NAME":"도동JC","TURN_P":"1","UPDATEDATE":"20230519","REMARK":"","HIST_TYPE":"","HISTREMARK":""}},
{"type":"Feature","geometry":{"type":"Point","coordinates":[343123.19849999994,369525.8314999994]},"properties":{"NODE_ID":"1540033200","NODE_TYPE":"106","NODE_NAME":"북대구IC","TURN_P":"1","UPDATEDATE":"20230519","REMARK":"","HIST_TYPE":"","HISTREMARK":""}},
{"type":"Feature","geometry":{"type":"Point","coordinates":[208773.7156999996,521172.14460000023]},"properties":{"NODE_ID":"2440036200","NODE_TYPE":"106","NODE_NAME":"신갈JC","TURN_P":"1","UPDATEDATE":"20230519","REMARK":"","HIST_TYPE":"","HISTREMARK":""}},
{"type":"Feature","geometry":{"type":"Point","coordinates":[352338.0005999999,367200.33940000087]},"properties":{"NODE_ID":"1510017500","NODE_TYPE":"101","NODE_NAME":"동대구JC","TURN_P":"0","UPDATEDATE":"20230519","REMARK":"","HIST_TYPE":"","HISTREMARK":""}},
{"type":"Feature","geometry":{"type":"Point","coordinates":[242761.7171,416526.5638999995]},"properties":{"NODE_ID":"1830071700","NODE_TYPE":"106","NODE_NAME":"비룡IC","TURN_P":"1","UPDATEDATE":"20230519","REMARK":"","HIST_TYPE":"","HISTREMARK":""}},
{"type":"Feature","geometry":{"type":"Point","coordinates":[237358.0876000002,423022.1671999991]},"properties":{"NODE_ID":"1870001800","NODE_TYPE":"106","NODE_NAME":"회덕JC","TURN_P":"1","UPDATEDATE":"20230519","REMARK":"","HIST_TYPE":"","HISTREMARK":""}},
{"type":"Feature","geometry":{"type":"Point","coordinates":[240200.76769999973,418870.38079999946]},"properties":{"NODE_ID":"1870078100","NODE_TYPE":"106","NODE_NAME":"대전IC","TURN_P":"1","UPDATEDATE":"20230519","REMARK":"","HIST_TYPE":"","HISTREMARK":""}},
{"type":"Feature","geometry":{"type":"Point","coordinates":[234168.3119000001,447530.91410000063]},"properties":{"NODE_ID":"2710003500","NODE_TYPE":"106","NODE_NAME":"청주IC","TURN_P":"1","UPDATEDATE":"20230519","REMARK":"","HIST_TYPE":"","HISTREMARK":""}},
{"type":"Feature","geometry":{"type":"Point","coordinates":[390046.0515999999,324260.13010000065]},"properties":{"NODE_ID":"1960316900","NODE_TYPE":"106","NODE_NAME":"통도사IC","TURN_P":"1","UPDATEDATE":"20230519","REMARK":"","HIST_TYPE":"","HISTREMARK":""}},
{"type":"Feature","geometry":{"type":"Point","coordinates":[398360.3426999999,348646.2609000001]},"properties":{"NODE_ID":"1960317500","NODE_TYPE":"106","NODE_NAME":"활천IC","TURN_P":"0","UPDATEDATE":"20230519","REMARK":"","HIST_TYPE":"","HISTREMARK":""}},
{"type":"Feature","geometry":{"type":"Point","coordinates":[203704.9467000002,540616.0088999998]},"properties":{"NODE_ID":"1210000600","NODE_TYPE":"106","NODE_NAME":"양재IC","TURN_P":"0","UPDATEDATE":"20230519","REMARK":"","HIST_TYPE":"","HISTREMARK":""}},
{"type":"Feature","geometry":{"type":"Point","coordinates":[202534.96019999962,542715.0830000006]},"properties":{"NODE_ID":"1210023100","NODE_TYPE":"106","NODE_NAME":"서초IC","TURN_P":"0","UPDATEDATE":"20230519","REMARK":"","HIST_TYPE":"","HISTREMARK":""}},
{"type":"Feature","geometry":{"type":"Point","coordinates":[389830.676,301858.06310000084]},"properties":{"NODE_ID":"1400059600","NODE_TYPE":"106","NODE_NAME":"노포JC","TURN_P":"0","UPDATEDATE":"20230519","REMARK":"","HIST_TYPE":"","HISTREMARK":""}},
{"type":"Feature","geometry":{"type":"Point","coordinates":[389907.18010000046,323316.2329999991]},"properties":{"NODE_ID":"3880014200","NODE_TYPE":"106","NODE_NAME":"통도사IC","TURN_P":"0","UPDATEDATE":"20230519","REMARK":"","HIST_TYPE":"","HISTREMARK":""}},
{"type":"Feature","geometry":{"type":"Point","coordinates":[386280.5870000003,311005.41599999927]},"properties":{"NODE_ID":"3880146100","NODE_TYPE":"106","NODE_NAME":"양산IC","TURN_P":"1","UPDATEDATE":"20230519","REMARK":"","HIST_TYPE":"","HISTREMARK":""}},
{"type":"Feature","geometry":{"type":"Point","coordinates":[398441.7725999998,348242.8147999998]},"properties":{"NODE_ID":"1960317600","NODE_TYPE":"106","NODE_NAME":"활천IC","TURN_P":"1","UPDATEDATE":"20230519","REMARK":"","HIST_TYPE":"","HISTREMARK":""}},
{"type":"Feature","geometry":{"type":"Point","coordinates":[238637.71190000046,440458.0114999991]},"properties":{"NODE_ID":"2830020300","NODE_TYPE":"106","NODE_NAME":"청주JC","TURN_P":"0","UPDATEDATE":"20230519","REMARK":"","HIST_TYPE":"","HISTREMARK":""}},
{"type":"Feature","geometry":{"type":"Point","coordinates":[201724.56049999967,544607.4945999999]},"properties":{"NODE_ID":"1210036700","NODE_TYPE":"106","NODE_NAME":"반포IC","TURN_P":"0","UPDATEDATE":"20230519","REMARK":"","HIST_TYPE":"","HISTREMARK":""}},
{"type":"Feature","geometry":{"type":"Point","coordinates":[201635.76240000036,544885.0153999999]},"properties":{"NODE_ID":"1210039000","NODE_TYPE":"106","NODE_NAME":"반포IC","TURN_P":"0","UPDATEDATE":"20230519","REMARK":"","HIST_TYPE":"","HISTREMARK":""}},
{"type":"Feature","geometry":{"type":"Point","coordinates":[323335.03220000025,386828.6776999999]},"properties":{"NODE_ID":"3550061000","NODE_TYPE":"106","NODE_NAME":"남구미IC","TURN_P":"0","UPDATEDATE":"20230519","REMARK":"","HIST_TYPE":"","HISTREMARK":""}},
{"type":"Feature","geometry":{"type":"Point","coordinates":[391099.3866999997,296754.5183000006]},"properties":{"NODE_ID":"1400003200","NODE_TYPE":"106","NODE_NAME":"구서IC","TURN_P":"0","UPDATEDATE":"20230519","REMARK":"","HIST_TYPE":"","HISTREMARK":""}},
{"type":"Feature","geometry":{"type":"Point","coordinates":[219039.2633999996,462680.6497000009]},"properties":{"NODE_ID":"3010102600","NODE_TYPE":"106","NODE_NAME":"목천IC","TURN_P":"0","UPDATEDATE":"20230519","REMARK":"","HIST_TYPE":"","HISTREMARK":""}},
{"type":"Feature","geometry":{"type":"Point","coordinates":[337379.81599999964,367265.15949999914]},"properties":{"NODE_ID":"1540001000","NODE_TYPE":"106","NODE_NAME":"금호JC","TURN_P":"1","UPDATEDATE":"20230519","REMARK":"","HIST_TYPE":"","HISTREMARK":""}},
{"type":"Feature","geometry":{"type":"Point","coordinates":[343226.2609000001,369579.3948999997]},"properties":{"NODE_ID":"1540033300","NODE_TYPE":"106","NODE_NAME":"북대구IC","TURN_P":"1","UPDATEDATE":"20230519","REMARK":"","HIST_TYPE":"","HISTREMARK":""}},
{"type":"Feature","geometry":{"type":"Point","coordinates":[209068.35510638164,513780.6028757108]},"properties":{"NODE_ID":"2440328800","NODE_TYPE":"106","NODE_NAME":"기흥IC","TURN_P":"0","UPDATEDATE":"20241129","REMARK":"","HIST_TYPE":"NODE0004","HISTREMARK":""}},
{"type":"Feature","geometry":{"type":"Point","coordinates":[209019.16780315852,513694.5828049995]},"properties":{"NODE_ID":"2440331800","NODE_TYPE":"106","NODE_NAME":"기흥IC","TURN_P":"0","UPDATEDATE":"20241129","REMARK":"","HIST_TYPE":"NODE0001","HISTREMARK":""}},
{"type":"Feature","geometry":{"type":"Point","coordinates":[208779.6701601516,513325.0665340699]},"properties":{"NODE_ID":"2440036001","NODE_TYPE":"106","NODE_NAME":"기흥동탄IC","TURN_P":"1","UPDATEDATE":"20241129","REMARK":"","HIST_TYPE":"NODE0001","HISTREMARK":"2440036000"}},
{"type":"Feature","geometry":{"type":"Point","coordinates":[208764.04338901283,513334.2764103794]},"properties":{"NODE_ID":"2440036002","NODE_TYPE":"106","NODE_NAME":"기흥동탄IC","TURN_P":"0","UPDATEDATE":"20241129","REMARK":"","HIST_TYPE":"NODE0001","HISTREMARK":"2440036000"}},
{"type":"Feature","geometry":{"type":"Point","coordinates":[206995.87817762146,504904.8516519158]},"properties":{"NODE_ID":"2230154100","NODE_TYPE":"106","NODE_NAME":"오산IC","TURN_P":"0","UPDATEDATE":"20231218","REMARK":"","HIST_TYPE":"NODE0001","HISTREMARK":""}},
{"type":"Feature","geometry":{"type":"Point","coordinates":[207946.39879999962,534588.7409000006]},"properties":{"NODE_ID":"2040146000","NODE_TYPE":"106","NODE_NAME":"대왕판교IC","TURN_P":"0","UPDATEDATE":"20241129","REMARK":"","HIST_TYPE":"NODE0005","HISTREMARK":""}},
{"type":"Feature","geometry":{"type":"Point","coordinates":[206962.4198626021,504892.50245446496]},"properties":{"NODE_ID":"2230153700","NODE_TYPE":"106","NODE_NAME":"오산IC","TURN_P":"0","UPDATEDATE":"20231218","REMARK":"","HIST_TYPE":"NODE0001","HISTREMARK":""}},
{"type":"Feature","geometry":{"type":"Point","coordinates":[206962.56450884553,504853.8869554647]},"properties":{"NODE_ID":"2230153400","NODE_TYPE":"106","NODE_NAME":"오산IC","TURN_P":"0","UPDATEDATE":"20231218","REMARK":"","HIST_TYPE":"NODE0001","HISTREMARK":""}},
{"type":"Feature","geometry":{"type":"Point","coordinates":[206996.2541078513,504892.8560600183]},"properties":{"NODE_ID":"2230154000","NODE_TYPE":"106","NODE_NAME":"오산IC","TURN_P":"0","UPDATEDATE":"20231218","REMARK":"","HIST_TYPE":"NODE0001","HISTREMARK":""}},
{"type":"Feature","geometry":{"type":"Point","coordinates":[390855.4801000003,326850.7871000003]},"properties":{"NODE_ID":"1960465301","NODE_TYPE":"106","NODE_NAME":"서울주JC","TURN_P":"0","UPDATEDATE":"20241129","REMARK":"","HIST_TYPE":"NODE0005","HISTREMARK":""}},
{"type":"Feature","geometry":{"type":"Point","coordinates":[201491.29789999966,545305.6917000003]},"properties":{"NODE_ID":"1210042800","NODE_TYPE":"106","NODE_NAME":"잠원IC","TURN_P":"0","UPDATEDATE":"20230519","REMARK":"","HIST_TYPE":"","HISTREMARK":""}},
{"type":"Feature","geometry":{"type":"Point","coordinates":[208527.92142528185,512784.83100658125]},"properties":{"NODE_ID":"2330554300","NODE_TYPE":"106","NODE_NAME":"기흥동탄IC","TURN_P":"0","UPDATEDATE":"20240325","REMARK":"","HIST_TYPE":"NODE0001","HISTREMARK":""}},
{"type":"Feature","geometry":{"type":"Point","coordinates":[208549.890311112,512777.26624872565]},"properties":{"NODE_ID":"2330554400","NODE_TYPE":"106","NODE_NAME":"기흥동탄IC","TURN_P":"0","UPDATEDATE":"20240325","REMARK":"","HIST_TYPE":"NODE0001","HISTREMARK":""}},
{"type":"Feature","geometry":{"type":"Point","coordinates":[238393.76520000026,441408.0053000003]},"properties":{"NODE_ID":"2830018300","NODE_TYPE":"106","NODE_NAME":"청주JC","TURN_P":"0","UPDATEDATE":"20230519","REMARK":"","HIST_TYPE":"","HISTREMARK":""}},
{"type":"Feature","geometry":{"type":"Point","coordinates":[390478.15139999986,325588.8662999999]},"properties":{"NODE_ID":"1960464301","NODE_TYPE":"106","NODE_NAME":"서울주JC","TURN_P":"0","UPDATEDATE":"20241129","REMARK":"","HIST_TYPE":"NODE0005","HISTREMARK":""}},
{"type":"Feature","geometry":{"type":"Point","coordinates":[208866.54769104905,513790.890439804]},"properties":{"NODE_ID":"2440328900","NODE_TYPE":"106","NODE_NAME":"기흥IC","TURN_P":"0","UPDATEDATE":"20241129","REMARK":"","HIST_TYPE":"NODE0004","HISTREMARK":""}},
{"type":"Feature","geometry":{"type":"Point","coordinates":[260522.62899999972,409299.70519999973]},"properties":{"NODE_ID":"2760197900","NODE_TYPE":"106","NODE_NAME":"금강IC","TURN_P":"0","UPDATEDATE":"20231013","REMARK":"","HIST_TYPE":"NODE0005","HISTREMARK":""}},
{"type":"Feature","geometry":{"type":"Point","coordinates":[210795.0416000001,501148.3071999997]},"properties":{"NODE_ID":"2430111101","NODE_TYPE":"101","NODE_NAME":"남사IC","TURN_P":"0","UPDATEDATE":"20241129","REMARK":"","HIST_TYPE":"NODE0005","HISTREMARK":""}},
{"type":"Feature","geometry":{"type":"Point","coordinates":[210438.71980000008,500505.3616000004]},"properties":{"NODE_ID":"2430110901","NODE_TYPE":"101","NODE_NAME":"남사IC","TURN_P":"0","UPDATEDATE":"20241129","REMARK":"","HIST_TYPE":"NODE0005","HISTREMARK":""}},
{"type":"Feature","geometry":{"type":"Point","coordinates":[352476.8968000002,366248.5081999991]},"properties":{"NODE_ID":"1510002800","NODE_TYPE":"101","NODE_NAME":"동대구JC","TURN_P":"0","UPDATEDATE":"20241129","REMARK":"","HIST_TYPE":"NODE0005","HISTREMARK":""}},
{"type":"Feature","geometry":{"type":"Point","coordinates":[208500.19341992695,509305.1174835658]},"properties":{"NODE_ID":"2330552700","NODE_TYPE":"106","NODE_NAME":"동탄JC","TURN_P":"0","UPDATEDATE":"20240325","REMARK":"","HIST_TYPE":"NODE0001","HISTREMARK":""}},
{"type":"Feature","geometry":{"type":"Point","coordinates":[334497.40440000035,369196.47250000015]},"properties":{"NODE_ID":"3690223901","NODE_TYPE":"101","NODE_NAME":"칠곡JC","TURN_P":"0","UPDATEDATE":"20230519","REMARK":"","HIST_TYPE":"","HISTREMARK":""}}
]}